aishell/__init__.py
aishell/__main__.py
aishell/backend.py
aishell/backend_factory.py
aishell/config.py
aishell/construct_prompt.py
aishell/shell.py
aishell/ora/__init__.py
aishell/ora/model.py
aishell/ora/typing.py
freeai_shell-0.1.dist-info/LICENSE
freeai_shell-0.1.dist-info/METADATA
freeai_shell-0.1.dist-info/WHEEL
freeai_shell-0.1.dist-info/dependency_links.txt
freeai_shell-0.1.dist-info/entry_points.txt
freeai_shell-0.1.dist-info/top_level.txt
freeai_shell-0.1.dist-info/RECORD
